sisa/__init__.py
sisa/puco.py
sisa/puco_cli.py
sisa/renaper.py
sisa/settings.py
sisa-0.922.dist-info/LICENSE
sisa-0.922.dist-info/METADATA
sisa-0.922.dist-info/WHEEL
sisa-0.922.dist-info/entry_points.txt
sisa-0.922.dist-info/top_level.txt
sisa-0.922.dist-info/RECORD
