Metadata-Version: 2.1
Name: sisa
Version: 0.922
Summary: SISA APIs tools
Home-page: https://github.com/cluster311/sisa
Author: Andres Vazquez
Author-email: andres@data99.com.ar
License: MIT
Platform: UNKNOWN
Classifier: Programming Language :: Python :: 3
Classifier: Programming Language :: Python :: 3.6
Classifier: License :: OSI Approved :: MIT License
Classifier: Operating System :: OS Independent
Classifier: Intended Audience :: Developers
Requires-Python: >=3.6
